huajiweb/ConfigOption.py
huajiweb/DeltaGenerator.py
huajiweb/ForwardMsgCache.py
huajiweb/MediaFileManager.py
huajiweb/Report.py
huajiweb/ReportQueue.py
huajiweb/ReportSession.py
huajiweb/ReportThread.py
huajiweb/ScriptRequestQueue.py
huajiweb/ScriptRunner.py
huajiweb/UploadedFileManager.py
huajiweb/__init__.py
huajiweb/bootstrap.py
huajiweb/caching.py
huajiweb/case_converters.py
huajiweb/cli.py
huajiweb/code_util.py
huajiweb/config.py
huajiweb/credentials.py
huajiweb/cursor.py
huajiweb/development.py
huajiweb/env_util.py
huajiweb/error_util.py
huajiweb/errors.py
huajiweb/file_util.py
huajiweb/folder_black_list.py
huajiweb/hashing.py
huajiweb/js_number.py
huajiweb/logger.py
huajiweb/magic.py
huajiweb/metrics.py
huajiweb/net_util.py
huajiweb/policy.py
huajiweb/source_util.py
huajiweb/string_util.py
huajiweb/temporary_directory.py
huajiweb/type_util.py
huajiweb/url_util.py
huajiweb/util.py
huajiweb/version.py
huajiweb/widgets.py
huajiweb/elements/__init__.py
huajiweb/elements/altair.py
huajiweb/elements/bokeh_chart.py
huajiweb/elements/data_frame_proto.py
huajiweb/elements/deck_gl.py
huajiweb/elements/deck_gl_json_chart.py
huajiweb/elements/doc_string.py
huajiweb/elements/exception_proto.py
huajiweb/elements/graphviz_chart.py
huajiweb/elements/image_proto.py
huajiweb/elements/map.py
huajiweb/elements/media_proto.py
huajiweb/elements/plotly_chart.py
huajiweb/elements/pyplot.py
huajiweb/elements/vega_lite.py
huajiweb/elements/lib/__init__.py
huajiweb/elements/lib/dicttools.py
huajiweb/hello/__init__.py
huajiweb/hello/demos.py
huajiweb/hello/hello.py
huajiweb/proto/Alert_pb2.py
huajiweb/proto/Audio_pb2.py
huajiweb/proto/BackMsg_pb2.py
huajiweb/proto/Balloons_pb2.py
huajiweb/proto/BlockPath_pb2.py
huajiweb/proto/BokehChart_pb2.py
huajiweb/proto/Button_pb2.py
huajiweb/proto/Chart_pb2.py
huajiweb/proto/Checkbox_pb2.py
huajiweb/proto/DataFrame_pb2.py
huajiweb/proto/DataTransform_pb2.py
huajiweb/proto/DateInput_pb2.py
huajiweb/proto/DeckGlChart_pb2.py
huajiweb-0.60.dist-info/METADATA
huajiweb-0.60.dist-info/WHEEL
huajiweb-0.60.dist-info/entry_points.txt
huajiweb-0.60.dist-info/top_level.txt
huajiweb-0.60.dist-info/RECORD
